{
  "catalogName": "My Fire TV App Catalog",
  "lastUpdatedUtc": "2026-03-28T00:00:00Z",
  "packages": [
    {
      "id": "tivimate",
      "name": "Tivimate",
      "version": "5.1",
      "description": "Tivimate.",
      "launchTarget": "ar.tvplayer.tv",
      "downloadUrl": "https://github.com/wiked1982/apk-cat/releases/download/apk/TiviMate_WFRZUY44M4_2200.apk"
    },
    {
      "id": "wicked",
      "name": "Wicked",
      "version": "4.1",
      "description": "Wicked.",
      "launchTarget": "com.wickedtv.wickedtvbox",
      "downloadUrl": "https://github.com/wiked1982/apk-cat/releases/download/apk/wickedtv.apk"
    },
     {
      "id": "into-dark",
      "name": "Into the Dark VPN",
      "version": "3.0.2",
      "description": "Stand alonv VPN. To be used if you experience buffering not related to internet spped. Into the Dark VPN. Contact Seller for login Credentials.",
      "downloadUrl": "https://github.com/wiked1982/apk-cat/releases/download/apk/IntoTheDark.3.0.2.apk"
    }
  ]
}
